eis_stripe_package/__init__.py
eis_stripe_package/common/__init__.py
eis_stripe_package/common/conversion_service/__init__.py
eis_stripe_package/common/conversion_service/currency_conversion.py
eis_stripe_package/common/conversion_service/date_conversion.py
eis_stripe_package/common/exception_service/__init__.py
eis_stripe_package/common/exception_service/custom_exception_handler.py
eis_stripe_package/one_time_payment/__init__.py
eis_stripe_package/one_time_payment/services.py
eis_stripe_package/one_time_payment/utils.py
eis_stripe_package/stripeAPI/__init__.py
eis_stripe_package/stripeAPI/utils.py
eis_stripe_package/stripeAPI/common/__init__.py
eis_stripe_package/stripeAPI/common/conversion_service/__init__.py
eis_stripe_package/stripeAPI/common/conversion_service/currency_conversion.py
eis_stripe_package/stripeAPI/common/conversion_service/date_conversion.py
eis_stripe_package/stripeAPI/common/exception_service/__init__.py
eis_stripe_package/stripeAPI/common/exception_service/custom_exception_handler.py
eis_stripe_package/stripeAPI/coupon/__init__.py
eis_stripe_package/stripeAPI/coupon/coupon.py
eis_stripe_package/stripeAPI/coupon/utils.py
eis_stripe_package/stripeAPI/customer/__init__.py
eis_stripe_package/stripeAPI/customer/customer.py
eis_stripe_package/stripeAPI/customer/utils.py
eis_stripe_package/stripeAPI/invoice/__init__.py
eis_stripe_package/stripeAPI/invoice/invoice.py
eis_stripe_package/stripeAPI/invoice/utils.py
eis_stripe_package/stripeAPI/invoice_item/__init__.py
eis_stripe_package/stripeAPI/invoice_item/invoice_item.py
eis_stripe_package/stripeAPI/invoice_item/utils.py
eis_stripe_package/stripeAPI/payment_method/__init__.py
eis_stripe_package/stripeAPI/payment_method/paymeny_method.py
eis_stripe_package/stripeAPI/payment_method/utils.py
eis_stripe_package/stripeAPI/paymeny_intent/__init__.py
eis_stripe_package/stripeAPI/paymeny_intent/paymeny_intent.py
eis_stripe_package/stripeAPI/paymeny_intent/utils.py
eis_stripe_package-1.0.4.dist-info/LICENSE
eis_stripe_package-1.0.4.dist-info/METADATA
eis_stripe_package-1.0.4.dist-info/WHEEL
eis_stripe_package-1.0.4.dist-info/top_level.txt
eis_stripe_package-1.0.4.dist-info/RECORD
