Metadata-Version: 2.1
Name: eis-stripe-package
Version: 1.0.4
Summary: stripe package for faster processing.
Home-page: UNKNOWN
Author: Stoneagefireball
Author-email: patelsoham22@gmail.com
License: UNKNOWN
Keywords: python
Platform: UNKNOWN
Classifier: Development Status :: 1 - Planning
Classifier: Intended Audience :: Developers
Classifier: Programming Language :: Python :: 3
Classifier: Operating System :: Unix
Classifier: Operating System :: MacOS :: MacOS X
Classifier: Operating System :: Microsoft :: Windows
License-File: LICENSE
Requires-Dist: stripe (==4.2)
